{
  "publishDate": "2024-06-18",
  "title": "Radio Interview: Chris Fabry Live",
  "subtitle": "Encouragement for Caregivers",
  "description": "Did you know that one out of five Americans has been or is now a caregiver? Author and speaker Debbie Barr will talk about the joys and struggles of caring for a family member or friend. She says all caregivers need support but many reach the point of exhaustion and even depression before they realize it.",
  "linkText": "Listen",
  "usePlayIcon": true,
  "link": "https://www.moodyradio.org/programs/chris-fabry-live/2024/06/18-encouragement-for-caregivers/"
}
